hh_api/__init__.py
hh_api/client.py
hh_api/exceptions.py
hh_api/utils.py
hh_api/version.py
hh_api/auth/__init__.py
hh_api/auth/exceptions.py
hh_api/auth/keyed_stores.py
hh_api/auth/locks.py
hh_api/auth/models.py
hh_api/auth/stores.py
hh_api/auth/token_manager.py
hh_api/auth/utils.py
hh_api-0.1.4.dist-info/METADATA
hh_api-0.1.4.dist-info/WHEEL
hh_api-0.1.4.dist-info/licenses/LICENSE
hh_api-0.1.4.dist-info/RECORD
